MANIFEST.in
README.rst
setup.cfg
setup.py
versioneer.py
stanity/__init__.py
stanity/_version.py
stanity/fit.py
stanity/psis.py
stanity/psisloo.py
stanity/utilities.py
stanity.egg-info/PKG-INFO
stanity.egg-info/SOURCES.txt
stanity.egg-info/dependency_links.txt
stanity.egg-info/requires.txt
stanity.egg-info/top_level.txt
test/test_fit.py
test/test_psisloo.py