Metadata-Version: 1.1
Name: stanity
Version: 0.1.4
Summary: Helper library for working with Stan models in Python
Home-page: https://github.com/hammerlab/stanity
Author: Jacki Buros and Tim O'Donnell
Author-email: timodonnell@gmail.com
License: Apache License
Download-URL: https://github.com/hammerlab/stanity/tarball/0.1.4
Platform: UNKNOWN
Classifier: Development Status :: 1 - Planning
Classifier: Intended Audience :: Developers
Classifier: License :: OSI Approved :: Apache Software License
Classifier: Programming Language :: Python :: 2
Classifier: Programming Language :: Python :: 2.7
Classifier: Programming Language :: Python :: 3
Classifier: Programming Language :: Python :: 3.4
